kpass/__init__.py
kpass/main.py
kpass_gen-0.2.6.dist-info/licenses/LICENSE.txt
kpass_gen-0.2.6.dist-info/METADATA
kpass_gen-0.2.6.dist-info/WHEEL
kpass_gen-0.2.6.dist-info/top_level.txt
kpass_gen-0.2.6.dist-info/RECORD
