Metadata-Version: 2.4
Name: kpass-gen
Version: 0.2.6
Summary: kpass is a Python toolkit for generating, ciphering and evaluating passwords with JSON, CSV and YAML export.
Author-email: "Lucas Paulino Da Silva (~K')" <lucas.workps@gmail.com>
License: MIT License
Project-URL: homepage, https://github.com/lucaspy-stack/kpass
Project-URL: repository, https://github.com/lucaspy-stack/kpass
Keywords: password,generator,leet,name-based,cybersecurity,pentest,automation,security,rich,csv,yaml,json,python
Classifier: Development Status :: 4 - Beta
Classifier: Intended Audience :: Developers
Classifier: Topic :: Security :: Cryptography
Classifier: Topic :: Software Development :: Libraries :: Python Modules
Classifier: License :: OSI Approved :: MIT License
Classifier: Operating System :: OS Independent
Classifier: Programming Language :: Python :: 3
Classifier: Programming Language :: Python :: 3.6
Classifier: Programming Language :: Python :: 3.7
Classifier: Programming Language :: Python :: 3.8
Classifier: Programming Language :: Python :: 3.9
Classifier: Programming Language :: Python :: 3.10
Classifier: Programming Language :: Python :: 3.11
Classifier: Programming Language :: Python :: 3.12
Requires-Python: >=3.6
License-File: LICENSE.txt
Requires-Dist: rich
Dynamic: license-file
